datapizza/tools/duckduckgo/__init__.py
datapizza/tools/duckduckgo/base.py
datapizza_ai_tools_duckduckgo-0.0.4.dist-info/METADATA
datapizza_ai_tools_duckduckgo-0.0.4.dist-info/WHEEL
datapizza_ai_tools_duckduckgo-0.0.4.dist-info/RECORD
