Metadata-Version: 2.4
Name: datapizza-ai-tools-duckduckgo
Version: 0.0.4
Summary: Azure Document Intelligence parser for the datapizza-ai framework
Author-email: Datapizza <datapizza@datapizza.tech>
License: MIT
Classifier: License :: OSI Approved :: MIT License
Classifier: Operating System :: OS Independent
Classifier: Programming Language :: Python :: 3
Requires-Python: <4,>=3.10.0
Requires-Dist: datapizza-ai-core<0.1.0,>=0.0.1
Requires-Dist: ddgs>=9.6.0
